peduncle/__init__.py
peduncle/grader.py
peduncle/peduncle.py
peduncle-0.0.2.dist-info/METADATA
peduncle-0.0.2.dist-info/WHEEL
peduncle-0.0.2.dist-info/licenses/LICENSE
peduncle-0.0.2.dist-info/RECORD
