Metadata-Version: 2.1
Name: peduncle
Version: 0.0.2
Summary: Simple Python content extractor for html
Project-URL: Homepage, https://github.com/midstreeeam/peduncle
Project-URL: Bug Tracker, https://github.com/midstreeeam/peduncle/issues
Author-email: Midstream <midstream.lou@gmail.com>
License-File: LICENSE
Classifier: License :: OSI Approved :: MIT License
Classifier: Operating System :: OS Independent
Classifier: Programming Language :: Python :: 3
Requires-Python: >=3.7
